CHANGES.rst
COPYRIGHT
LICENSE
MANIFEST.in
README.rst
RELEASING.rst
message-extraction.ini
setup.cfg
setup.py
pyramid_yards/__init__.py
pyramid_yards/yards.py
pyramid_yards.egg-info/PKG-INFO
pyramid_yards.egg-info/SOURCES.txt
pyramid_yards.egg-info/dependency_links.txt
pyramid_yards.egg-info/not-zip-safe
pyramid_yards.egg-info/requires.txt
pyramid_yards.egg-info/top_level.txt
pyramid_yards/locales/pyramid-yards.pot
pyramid_yards/locales/en/LC_MESSAGES/pyramid-yards.mo
pyramid_yards/locales/en/LC_MESSAGES/pyramid-yards.po
pyramid_yards/locales/es/LC_MESSAGES/pyramid-yards.mo
pyramid_yards/locales/es/LC_MESSAGES/pyramid-yards.po
pyramid_yards/locales/fr/LC_MESSAGES/pyramid-yards.mo
pyramid_yards/locales/fr/LC_MESSAGES/pyramid-yards.po
pyramid_yards/locales/zh/LC_MESSAGES/pyramid-yards.mo
pyramid_yards/locales/zh/LC_MESSAGES/pyramid-yards.po