Metadata-Version: 1.1
Name: pyramid-yards
Version: 0.10
Summary: Pyramid Request Parameter Validation
Home-page: https://github.com/Gandi/pyramid_yards
Author: Guillaume Gauvrit
Author-email: guillaume@gauvr.it
License: BSD-derived (http://www.repoze.org/LICENSE.txt)
Keywords: pyramid colander
Platform: UNKNOWN
Classifier: Programming Language :: Python
Classifier: Framework :: Pyramid
Classifier: Topic :: Internet :: WWW/HTTP
Classifier: Topic :: Internet :: WWW/HTTP :: WSGI :: Application
Classifier: Intended Audience :: Developers
Classifier: License :: Repoze Public License
